pyosmogps/__init__.py
pyosmogps/__main__.py
pyosmogps/data_filters.py
pyosmogps/dji_pb2.py
pyosmogps/ffmpeg_manager.py
pyosmogps/main.py
pyosmogps/metadata_manager.py
pyosmogps/pyosmogps.py
pyosmogps-0.1.0.dist-info/LICENSE
pyosmogps-0.1.0.dist-info/METADATA
pyosmogps-0.1.0.dist-info/WHEEL
pyosmogps-0.1.0.dist-info/entry_points.txt
pyosmogps-0.1.0.dist-info/top_level.txt
pyosmogps-0.1.0.dist-info/RECORD
