Metadata-Version: 2.2
Name: pyosmogps
Version: 0.1.0
Summary: Extract the GPS data from the Osmo Action video files
Home-page: https://github.com/francescocaponio/pyosmogps
Author: Francesco Caponio
Project-URL: Source Code, https://github.com/francescocaponio/pyosmogps
Project-URL: Change Log, https://github.com/francescocaponio/pyosmogps/blob/main/CHANGELOG.md
Classifier: Programming Language :: Python :: 3 :: Only
Classifier: Programming Language :: Python :: 3.8
Classifier: Programming Language :: Python :: 3.9
Requires-Python: >=3.8
License-File: LICENSE
Requires-Dist: protobuf
Requires-Dist: dateutils
Requires-Dist: gpxpy
Requires-Dist: numpy
Requires-Dist: scipy
